Metadata-Version: 1.1
Name: Flask-SSLify
Version: 0.1.0
Summary: Force SSL on your Flask app.
Home-page: https://github.com/kennethreitz/flask-sslify
Author: Kenneth Reitz
Author-email: me@kennethreitz.com
License: BSD
Platform: any
Classifier: Environment :: Web Environment
Classifier: Intended Audience :: Developers
Classifier: License :: OSI Approved :: BSD License
Classifier: Operating System :: OS Independent
Classifier: Programming Language :: Python
Classifier: Topic :: Internet :: WWW/HTTP :: Dynamic Content
Classifier: Topic :: Software Development :: Libraries :: Python Modules
